RestClient4py/__init__.py
RestClient4py/client.py
RestClient4py-1.0.13.dist-info/METADATA
RestClient4py-1.0.13.dist-info/WHEEL
RestClient4py-1.0.13.dist-info/top_level.txt
RestClient4py-1.0.13.dist-info/RECORD
